{"code_vue2_395.md":"03b1fjp7","code_webpack4_377.md":"D_JYHhwT","code_webpack4_385.md":"99y11ZyU","exp_188.md":"TT-XxFJg","exp_209.md":"nFJiOc7j","exp_203.md":"Eiu2SDIE","code_vue2_392.md":"44losn0S","code_webpack4_378.md":"VZxMa6mN","exp_218.md":"TCqb_flT","exp_208.md":"pHwO4EH2","exp_348.md":"YLJErZwi","code_webpack4_384.md":"7a6w7b6I","code_webpack4_379.md":"DuyV2Yxf","code_webpack4_376.md":"AuCjJY-r","exp_204.md":"1YZHbdVz","code_webpack4_373.md":"7n9oCSRF","exp_407.md":"xcS4ogG3","exp_210.md":"MaTHT2Oa","exp_187.md":"wzVRn-_E","code_webpack4_381.md":"3JJsSWv-","code_webpack4_374.md":"rn1sj_k4","exp_358.md":"HPzCFNaH","exp_366.md":"9ec7RA82","exp_186.md":"vsoGu-3N","code_webpack4_380.md":"ktXMHeoH","code_vue2_401.md":"bpa8dJ_i","code_vue2_399.md":"WU-ISeg0","exp_408.md":"tAtz_5Pi","code_vue2_398.md":"v49X86wa","code_vue2_394.md":"_Kh8RVXZ","exp_405.md":"_V9dd2jT","exp_361.md":"_MnpCvBr","index.md":"VleFjLpT","exp_416.md":"Wv22o3Yz","code_vue2_393.md":"U-btOM0b","code_webpack4_372.md":"BhfVo3z7","misc_230.md":"1FWT0rbP","code_vue2_400.md":"z23yrykU","code_webpack4_382.md":"QQc6AEkQ","exp_336.md":"34ntWhKm","code_vue2_396.md":"Sj_Zkq98","code_webpack4_375.md":"Uhjc_24z","exp_390.md":"WIWgRjnB","exp_411.md":"QofbwfCO","exp_347.md":"CInTfU7b","micro_999.md":"4IxCgGLO","code_vue2_397.md":"MkjEqQjA","misc_226.md":"_0GoBagY","misc_237.md":"4mKGxkz_","exp_414.md":"lzBSrgtR","misc_273.md":"zwX4T7d4","misc_349.md":"labB7zb1","misc_254.md":"rc4MEIeC","exp_359.md":"ULyUHsdM","code_webpack4_383.md":"2WrUqObW","misc_362.md":"lnk8WCv8","misc_410.md":"l7FsS4V5","misc_364.md":"mbtjeNNd","misc_346.md":"NuCxU4H6","misc_363.md":"i5Z-ouoY","misc_356.md":"y_pvX2vB","misc_257.md":"gD8xMzvO","misc_303.md":"th2ZFeZE","misc_351.md":"VTm38l4v","misc_388.md":"HNQxtK_H","misc_352.md":"0Zx30gQh","misc_389.md":"8_WXYgWY","misc_340.md":"CnHBdnNQ","misc_317.md":"0vUO50Ig","misc_333.md":"hHx2Ccki","misc_325.md":"eXbsoC36","misc_386.md":"ZkjwESnJ","misc_413.md":"LeyFBNi4","misc_387.md":"6a_D139R","misc_391.md":"YsjlsSW2","misc_402.md":"r4EMxDSm","misc_259.md":"IY3pXk9v","misc_355.md":"JDwD13Hg","misc_371.md":"lfS2QOXl","misc_403.md":"KpRc3DNX","misc_357.md":"_4NVtrVR","misc_409.md":"NR_yZDpa","misc_370.md":"n7QaMZj6","misc_406.md":"3N8BFIzW","misc_404.md":"BdgSs3vd","misc_368.md":"VQkZJuEq","misc_367.md":"tGvGiDN7","misc_369.md":"TxbWKy7l","misc_277.md":"DaeCZA9a","misc_240.md":"V0P_EkkP","misc_312.md":"aS_eHLYt","misc_365.md":"-c9lUZJr","misc_360.md":"dA7Dls99"}
